scidbbridge/__init__.py
scidbbridge/bridge-v1to3-fix.py
scidbbridge/coord.py
scidbbridge/coord_perf.py
scidbbridge/driver.py
scidb_bridge-19.11.7.dist-info/LICENSE.txt
scidb_bridge-19.11.7.dist-info/METADATA
scidb_bridge-19.11.7.dist-info/WHEEL
scidb_bridge-19.11.7.dist-info/top_level.txt
scidb_bridge-19.11.7.dist-info/RECORD
