Metadata-Version: 2.1
Name: scidb-bridge
Version: 19.11.7
Summary: Python library to access externally stored SciDB data
Download-URL: http://github.com/Paradigm4/bridge
Author: Rares Vernica
Author-email: rvernica@gmail.com
License: AGPL-3.0
Classifier: Development Status :: 4 - Beta
Classifier: Environment :: Console
Classifier: Intended Audience :: Science/Research
Classifier: License :: OSI Approved :: GNU Affero General Public License v3
Classifier: Natural Language :: English
Classifier: Programming Language :: Python :: 3.5
Classifier: Programming Language :: Python :: 3.6
Classifier: Programming Language :: Python :: 3.7
Classifier: Programming Language :: Python :: 3.8
Classifier: Programming Language :: Python :: 3.9
Classifier: Programming Language :: Python :: 3.10
Classifier: Topic :: Database :: Front-Ends
Classifier: Topic :: Scientific/Engineering
License-File: LICENSE.txt
Requires-Dist: boto3 >=1.14.12
Requires-Dist: pyarrow <=11.0.0,>=5.0.0
Requires-Dist: scidb-py >=19.11.7
